odoo/addons/carrier_account_environment/README.rst
odoo/addons/carrier_account_environment/__init__.py
odoo/addons/carrier_account_environment/__manifest__.py
odoo/addons/carrier_account_environment/i18n/carrier_account_environment.pot
odoo/addons/carrier_account_environment/i18n/carrier_environment.pot
odoo/addons/carrier_account_environment/models/__init__.py
odoo/addons/carrier_account_environment/models/carrier_account.py
odoo/addons/carrier_account_environment/readme/CONFIGURE.rst
odoo/addons/carrier_account_environment/readme/CONTRIBUTORS.rst
odoo/addons/carrier_account_environment/readme/DESCRIPTION.rst
odoo/addons/carrier_account_environment/readme/USAGE.rst
odoo/addons/carrier_account_environment/static/description/icon.png
odoo/addons/carrier_account_environment/static/description/index.html
odoo14_addon_carrier_account_environment-14.0.1.0.1.dist-info/METADATA
odoo14_addon_carrier_account_environment-14.0.1.0.1.dist-info/WHEEL
odoo14_addon_carrier_account_environment-14.0.1.0.1.dist-info/top_level.txt
odoo14_addon_carrier_account_environment-14.0.1.0.1.dist-info/RECORD
